_zipdecrypter.pypy39-pp73-darwin.so
fast_zip_decryption.py
fast_zip_decryption-3.0.0.dist-info/RECORD
fast_zip_decryption-3.0.0.dist-info/LICENSE
fast_zip_decryption-3.0.0.dist-info/WHEEL
fast_zip_decryption-3.0.0.dist-info/top_level.txt
fast_zip_decryption-3.0.0.dist-info/METADATA
