Metadata-Version: 2.1
Name: fast-zip-decryption
Version: 3.0.0
Summary: Read password protected Zips 100x faster
Author-email: Maximilian Knespel <mxmlnkn@no-reply.github.com>
License: MIT
Project-URL: Homepage, https://github.com/mxmlnkn/fast-zip-decryption
Keywords: zip,zipfile,fastzip
Classifier: Development Status :: 4 - Beta
Classifier: Intended Audience :: Developers
Classifier: Topic :: System :: Archiving
Classifier: Topic :: System :: Archiving :: Compression
Classifier: Topic :: Utilities
Classifier: License :: OSI Approved :: MIT License
Classifier: Operating System :: MacOS
Classifier: Operating System :: Unix
Classifier: Operating System :: Microsoft :: Windows
Classifier: Programming Language :: Python :: 3
Classifier: Programming Language :: Python :: 3.4
Classifier: Programming Language :: Python :: 3.5
Classifier: Programming Language :: Python :: 3.6
Classifier: Programming Language :: Python :: 3.7
Classifier: Programming Language :: Python :: 3.8
Requires-Python: >=3.8
License-File: LICENSE
